mcsrvstat/__init__.py
mcsrvstat/exceptions.py
mcsrvstat/ext.py
mcsrvstat/main.py
api.mcsrvstat.py-2023.9.4.dist-info/LICENSE
api.mcsrvstat.py-2023.9.4.dist-info/METADATA
api.mcsrvstat.py-2023.9.4.dist-info/WHEEL
api.mcsrvstat.py-2023.9.4.dist-info/top_level.txt
api.mcsrvstat.py-2023.9.4.dist-info/RECORD
