Metadata-Version: 2.1
Name: api.mcsrvstat.py
Version: 2023.9.4
Summary: An asynchronous Python wrapper for the Minecraft Server Status API.
Home-page: https://github.com/hitblast/api.mcsrvstat.py
Author: HitBlast
Author-email: <hitblastlive@gmail.com>
Keywords: python,minecraft,mcsrvstat
Classifier: Development Status :: 5 - Production/Stable
Classifier: License :: OSI Approved :: MIT License
Classifier: Intended Audience :: Developers
Classifier: Operating System :: OS Independent
Classifier: Programming Language :: Python :: 3.8
Classifier: Programming Language :: Python :: 3.9
Classifier: Programming Language :: Python :: 3.10
Classifier: Programming Language :: Python :: 3.11
Classifier: Topic :: Software Development :: Libraries :: Python Modules
Requires-Python: >=3.8
License-File: LICENSE
Requires-Dist: aiohttp ==3.8.5
Requires-Dist: Pillow ==10.0.0
